{
    "abd": {
        "o": 1
    },
    "ach": {
        "e": 1
    },
    "ada": {
        "m": 1
    },
    "add": {
        "e": 1
    },
    "ade": {
        "s": 1
    },
    "agu": {
        "s": 1
    },
    "ail": {
        "s": 1
    },
    "ais": {
        "t": 1
    },
    "all": {
        "b": 1
    },
    "alm": {
        "s": 1
    },
    "alv": {
        "e": 1
    },
    "ams": {
        "a": 1
    },
    "ani": {
        "n": 1
    },
    "ank": {
        "l": 1
    },
    "anu": {
        "s": 1
    },
    "aph": {
        "r": 1
    },
    "app": {
        "l": 1
    },
    "arb": {
        "o": 1
    },
    "arl": {
        "o": 1
    },
    "ary": {
        "n": 1
    },
    "ash": {
        "e": 1
    },
    "ave": {
        "l": 1
    },
    "avi": {
        "c": 1
    },
    "bdo": {
        "m": 1
    },
    "bel": {
        "l": 2
    },
    "big": {
        "t": 1
    },
    "bla": {
        "d": 2
    },
    "bon": {
        "e": 2
    },
    "bow": {
        "s": 1
    },
    "bre": {
        "a": 1
    },
    "bro": {
        "w": 1
    },
    "but": {
        "t": 2
    },
    "cal": {
        "f": 2,
        "p": 1,
        "v": 1
    },
    "can": {
        "i": 1
    },
    "che": {
        "a": 1,
        "e": 1,
        "s": 1
    },
    "chi": {
        "n": 1
    },
    "cla": {
        "v": 1
    },
    "cle": {
        "s": 2
    },
    "col": {
        "l": 1
    },
    "cro": {
        "t": 1
    },
    "ctu": {
        "m": 1
    },
    "dam": {
        "s": 1
    },
    "dde": {
        "r": 1
    },
    "der": {
        "b": 1,
        "s": 1
    },
    "dia": {
        "p": 1
    },
    "dne": {
        "y": 1
    },
    "dom": {
        "e": 1
    },
    "don": {
        "s": 1
    },
    "ear": {
        "l": 1
    },
    "eas": {
        "t": 1
    },
    "ebr": {
        "o": 1
    },
    "eca": {
        "p": 2
    },
    "ect": {
        "u": 1
    },
    "eec": {
        "a": 2
    },
    "eek": {
        "s": 1
    },
    "eet": {
        "h": 1
    },
    "ehe": {
        "a": 2
    },
    "ela": {
        "s": 1
    },
    "elb": {
        "o": 2
    },
    "eli": {
        "d": 1
    },
    "ell": {
        "y": 2
    },
    "end": {
        "o": 1
    },
    "eni": {
        "s": 1
    },
    "env": {
        "i": 1
    },
    "erb": {
        "l": 1
    },
    "ern": {
        "a": 1,
        "u": 1
    },
    "eso": {
        "p": 1
    },
    "est": {
        "i": 1
    },
    "eye": {
        "b": 1,
        "l": 2
    },
    "fee": {
        "t": 1
    },
    "fin": {
        "g": 2
    },
    "foo": {
        "t": 1
    },
    "for": {
        "e": 2
    },
    "gal": {
        "l": 1
    },
    "ger": {
        "n": 1
    },
    "gro": {
        "i": 1
    },
    "gto": {
        "e": 1
    },
    "gum": {
        "s": 1
    },
    "hag": {
        "u": 1
    },
    "hai": {
        "r": 1
    },
    "han": {
        "d": 1
    },
    "hea": {
        "d": 3
    },
    "hee": {
        "k": 1
    },
    "hes": {
        "t": 1
    },
    "hig": {
        "h": 2
    },
    "hin": {
        "b": 1
    },
    "hip": {
        "s": 1
    },
    "hou": {
        "l": 2
    },
    "hra": {
        "g": 1
    },
    "hro": {
        "a": 1
    },
    "hum": {
        "b": 1
    },
    "iap": {
        "h": 1
    },
    "ibi": {
        "a": 1
    },
    "icl": {
        "e": 1
    },
    "idn": {
        "e": 1
    },
    "igh": {
        "s": 1
    },
    "igt": {
        "o": 1
    },
    "inb": {
        "o": 1
    },
    "ine": {
        "s": 2
    },
    "ing": {
        "e": 2
    },
    "int": {
        "e": 1
    },
    "ipp": {
        "l": 1
    },
    "ive": {
        "r": 1
    },
    "kid": {
        "n": 1
    },
    "kne": {
        "e": 3
    },
    "kul": {
        "l": 1
    },
    "lad": {
        "d": 1,
        "e": 1
    },
    "lar": {
        "b": 1,
        "s": 1,
        "y": 1
    },
    "las": {
        "h": 1
    },
    "lav": {
        "i": 1
    },
    "lbl": {
        "a": 1
    },
    "lbo": {
        "w": 2
    },
    "lde": {
        "r": 2
    },
    "lee": {
        "n": 1
    },
    "lid": {
        "s": 1
    },
    "lip": {
        "s": 1
    },
    "liv": {
        "e": 1
    },
    "lla": {
        "r": 1
    },
    "llb": {
        "l": 1
    },
    "lly": {
        "b": 1
    },
    "lob": {
        "e": 1
    },
    "lve": {
        "s": 1
    },
    "lyb": {
        "u": 1
    },
    "mol": {
        "a": 1
    },
    "mou": {
        "t": 1
    },
    "msa": {
        "p": 1
    },
    "mus": {
        "c": 1
    },
    "nai": {
        "l": 2
    },
    "nav": {
        "e": 1
    },
    "nbo": {
        "n": 1
    },
    "ndo": {
        "n": 1
    },
    "nee": {
        "c": 2
    },
    "nge": {
        "r": 2
    },
    "ngu": {
        "e": 1
    },
    "nin": {
        "e": 1
    },
    "nip": {
        "p": 1
    },
    "nkl": {
        "e": 1
    },
    "nos": {
        "e": 1,
        "t": 1
    },
    "nte": {
        "s": 1
    },
    "nvi": {
        "s": 1
    },
    "obe": {
        "s": 1
    },
    "ock": {
        "s": 1
    },
    "ola": {
        "r": 1
    },
    "ole": {
        "s": 1
    },
    "oll": {
        "a": 1
    },
    "ome": {
        "n": 1
    },
    "ong": {
        "u": 1
    },
    "oot": {
        "h": 1
    },
    "oph": {
        "a": 1
    },
    "ore": {
        "h": 2
    },
    "ors": {
        "o": 1
    },
    "ost": {
        "r": 1
    },
    "otu": {
        "m": 1
    },
    "oul": {
        "d": 2
    },
    "out": {
        "h": 1
    },
    "pal": {
        "m": 1
    },
    "pen": {
        "i": 1,
        "v": 1
    },
    "pha": {
        "g": 1
    },
    "phr": {
        "a": 1
    },
    "pil": {
        "s": 1
    },
    "pin": {
        "e": 1
    },
    "ple": {
        "e": 1,
        "s": 1
    },
    "ppl": {
        "e": 2
    },
    "pup": {
        "i": 1
    },
    "rac": {
        "h": 1
    },
    "rag": {
        "m": 1
    },
    "rbl": {
        "a": 1
    },
    "rbo": {
        "n": 1
    },
    "rea": {
        "s": 1
    },
    "rec": {
        "t": 1
    },
    "reh": {
        "e": 2
    },
    "rib": {
        "s": 1
    },
    "ris": {
        "t": 1
    },
    "rlo": {
        "b": 1
    },
    "rna": {
        "i": 1
    },
    "rnu": {
        "m": 1
    },
    "roa": {
        "t": 1
    },
    "roi": {
        "n": 1
    },
    "rot": {
        "u": 1
    },
    "row": {
        "s": 1
    },
    "ryn": {
        "x": 1
    },
    "sap": {
        "p": 1
    },
    "sca": {
        "l": 1
    },
    "scl": {
        "e": 1
    },
    "scr": {
        "o": 1
    },
    "she": {
        "s": 1
    },
    "shi": {
        "n": 1
    },
    "sho": {
        "u": 2
    },
    "ski": {
        "n": 1
    },
    "sku": {
        "l": 1
    },
    "sol": {
        "e": 1
    },
    "sop": {
        "h": 1
    },
    "spi": {
        "n": 1
    },
    "spl": {
        "e": 1
    },
    "ste": {
        "r": 1
    },
    "sti": {
        "n": 1
    },
    "str": {
        "i": 1
    },
    "tee": {
        "t": 1
    },
    "ten": {
        "d": 1
    },
    "ter": {
        "n": 1
    },
    "tes": {
        "t": 1
    },
    "thi": {
        "g": 2
    },
    "thr": {
        "o": 1
    },
    "thu": {
        "m": 1
    },
    "tib": {
        "i": 1
    },
    "tin": {
        "e": 1
    },
    "toc": {
        "k": 1
    },
    "toe": {
        "s": 1
    },
    "ton": {
        "g": 1
    },
    "too": {
        "t": 1
    },
    "tor": {
        "s": 1
    },
    "tra": {
        "c": 1
    },
    "tri": {
        "l": 1
    },
    "tto": {
        "c": 1,
        "n": 1
    },
    "uld": {
        "e": 2
    },
    "ulv": {
        "a": 1
    },
    "upi": {
        "l": 1
    },
    "usc": {
        "l": 1
    },
    "utt": {
        "o": 2
    },
    "vic": {
        "l": 1
    },
    "vul": {
        "v": 1
    },
    "wai": {
        "s": 1
    },
    "wri": {
        "s": 1
    },
    "ybu": {
        "t": 1
    },
    "yeb": {
        "r": 1
    },
    "yel": {
        "a": 1,
        "i": 1
    }
}