{
    "aba": {
        "r": 3
    },
    "abe": {
        "a": 2
    },
    "abo": {
        "n": 1
    },
    "aca": {
        "d": 1
    },
    "ach": {
        "i": 1
    },
    "aci": {
        "n": 1
    },
    "ack": {
        "e": 1,
        "f": 1,
        "n": 1,
        "w": 1
    },
    "aco": {
        "r": 1
    },
    "ada": {
        "m": 1
    },
    "adb": {
        "e": 1
    },
    "adi": {
        "s": 1
    },
    "adn": {
        "u": 1
    },
    "agb": {
        "a": 1
    },
    "ain": {
        "a": 1
    },
    "aiz": {
        "e": 1
    },
    "ala": {
        "b": 3
    },
    "alm": {
        "e": 1,
        "n": 1,
        "o": 2
    },
    "aln": {
        "u": 3
    },
    "ama": {
        "r": 1
    },
    "amb": {
        "e": 1
    },
    "ami": {
        "a": 1
    },
    "amo": {
        "n": 1
    },
    "anb": {
        "e": 1
    },
    "and": {
        "l": 1
    },
    "ane": {
        "s": 1
    },
    "anh": {
        "a": 1
    },
    "ant": {
        "h": 1
    },
    "anu": {
        "t": 3
    },
    "anz": {
        "a": 1
    },
    "apa": {
        "n": 1
    },
    "apr": {
        "i": 1
    },
    "ara": {
        "d": 1,
        "l": 1,
        "n": 1
    },
    "arc": {
        "h": 1
    },
    "arg": {
        "o": 1
    },
    "arl": {
        "e": 1,
        "m": 1
    },
    "art": {
        "n": 1
    },
    "ash": {
        "e": 2
    },
    "ate": {
        "r": 1
    },
    "att": {
        "a": 1
    },
    "ava": {
        "b": 1
    },
    "aze": {
        "l": 2
    },
    "azi": {
        "l": 1
    },
    "bar": {
        "a": 1,
        "c": 1,
        "g": 1,
        "k": 1,
        "l": 1
    },
    "bea": {
        "n": 11
    },
    "bee": {
        "c": 2
    },
    "bla": {
        "c": 2
    },
    "bon": {
        "n": 1,
        "o": 1
    },
    "bop": {
        "p": 1
    },
    "bra": {
        "z": 1
    },
    "bre": {
        "a": 1
    },
    "bro": {
        "a": 1
    },
    "buc": {
        "k": 1
    },
    "bun": {
        "y": 1
    },
    "cad": {
        "a": 1
    },
    "cal": {
        "e": 1
    },
    "can": {
        "d": 1
    },
    "cas": {
        "h": 2
    },
    "cat": {
        "t": 1
    },
    "cem": {
        "p": 1
    },
    "che": {
        "s": 6
    },
    "chi": {
        "a": 1,
        "c": 1,
        "l": 1,
        "n": 1,
        "o": 1
    },
    "cil": {
        "l": 1
    },
    "cin": {
        "t": 1
    },
    "cke": {
        "y": 1
    },
    "ckf": {
        "r": 1
    },
    "ckn": {
        "u": 1
    },
    "cko": {
        "r": 1
    },
    "ckp": {
        "e": 1
    },
    "ckw": {
        "a": 1,
        "h": 1
    },
    "coa": {
        "b": 1
    },
    "coc": {
        "o": 2
    },
    "cof": {
        "f": 1
    },
    "col": {
        "o": 1
    },
    "com": {
        "m": 1
    },
    "con": {
        "u": 1
    },
    "cor": {
        "n": 1
    },
    "cow": {
        "p": 1
    },
    "cyn": {
        "t": 1
    },
    "dam": {
        "i": 1
    },
    "dbe": {
        "a": 2
    },
    "dia": {
        "n": 1
    },
    "dis": {
        "e": 1
    },
    "dle": {
        "n": 1
    },
    "dnu": {
        "t": 3
    },
    "dpe": {
        "a": 1
    },
    "dry": {
        "b": 1
    },
    "dur": {
        "i": 1
    },
    "ead": {
        "n": 1
    },
    "ean": {
        "h": 1,
        "s": 2,
        "u": 1
    },
    "ear": {
        "l": 1,
        "t": 1
    },
    "ebe": {
        "a": 1
    },
    "eca": {
        "n": 1
    },
    "ech": {
        "e": 2
    },
    "eda": {
        "k": 1
    },
    "edb": {
        "e": 1
    },
    "edp": {
        "e": 1
    },
    "eeb": {
        "e": 1
    },
    "eec": {
        "h": 2
    },
    "eet": {
        "c": 1
    },
    "ell": {
        "o": 1
    },
    "eln": {
        "u": 2
    },
    "elo": {
        "n": 1
    },
    "elv": {
        "e": 1
    },
    "emp": {
        "e": 1
    },
    "enu": {
        "t": 5
    },
    "eon": {
        "p": 1
    },
    "epi": {
        "t": 1
    },
    "erc": {
        "h": 1
    },
    "ers": {
        "e": 1,
        "g": 1
    },
    "esa": {
        "m": 1
    },
    "ese": {
        "c": 2
    },
    "est": {
        "n": 6
    },
    "etb": {
        "e": 1
    },
    "etc": {
        "h": 1
    },
    "ewn": {
        "u": 1
    },
    "eye": {
        "d": 1
    },
    "eyp": {
        "u": 1
    },
    "fav": {
        "a": 1
    },
    "fee": {
        "b": 1
    },
    "ffe": {
        "e": 1
    },
    "fla": {
        "x": 1
    },
    "flo": {
        "w": 1
    },
    "fon": {
        "i": 1
    },
    "fox": {
        "n": 1
    },
    "fru": {
        "i": 1
    },
    "gab": {
        "o": 1
    },
    "gba": {
        "r": 1
    },
    "gbo": {
        "n": 1
    },
    "ged": {
        "b": 1
    },
    "geo": {
        "n": 1
    },
    "ghu": {
        "m": 1
    },
    "gon": {
        "g": 1
    },
    "gou": {
        "r": 1
    },
    "gra": {
        "i": 1,
        "s": 1
    },
    "gro": {
        "u": 2
    },
    "hag": {
        "b": 1
    },
    "han": {
        "z": 1
    },
    "haz": {
        "e": 2
    },
    "hbe": {
        "a": 1
    },
    "hea": {
        "r": 1,
        "t": 2
    },
    "hem": {
        "p": 1
    },
    "hes": {
        "t": 6
    },
    "hew": {
        "n": 1
    },
    "hic": {
        "k": 2
    },
    "hil": {
        "e": 1
    },
    "hin": {
        "e": 1
    },
    "hya": {
        "c": 1
    },
    "ian": {
        "b": 1
    },
    "ica": {
        "l": 1
    },
    "ick": {
        "o": 1,
        "p": 1
    },
    "ico": {
        "t": 1
    },
    "ige": {
        "o": 1
    },
    "ile": {
        "a": 1
    },
    "ili": {
        "n": 1
    },
    "ill": {
        "e": 1,
        "o": 1
    },
    "iln": {
        "u": 1
    },
    "ina": {
        "m": 1
    },
    "ind": {
        "i": 1
    },
    "ine": {
        "n": 1,
        "s": 1
    },
    "ing": {
        "a": 1,
        "e": 1
    },
    "ino": {
        "a": 1
    },
    "int": {
        "h": 1
    },
    "inu": {
        "t": 1
    },
    "ise": {
        "n": 1
    },
    "ist": {
        "a": 1
    },
    "iti": {
        "c": 1
    },
    "its": {
        "e": 1
    },
    "jac": {
        "k": 2
    },
    "jap": {
        "a": 1
    },
    "key": {
        "e": 1,
        "p": 1
    },
    "kfr": {
        "u": 1
    },
    "knu": {
        "t": 1
    },
    "kol": {
        "a": 1
    },
    "kor": {
        "y": 1
    },
    "kpe": {
        "a": 1
    },
    "kwa": {
        "l": 1
    },
    "kwh": {
        "e": 1
    },
    "lab": {
        "a": 3
    },
    "lac": {
        "k": 2
    },
    "lan": {
        "u": 1
    },
    "lea": {
        "n": 1
    },
    "len": {
        "u": 3
    },
    "lin": {
        "u": 1
    },
    "lle": {
        "t": 1
    },
    "llo": {
        "w": 1
    },
    "lme": {
        "r": 1
    },
    "lmi": {
        "l": 1
    },
    "lmn": {
        "u": 1
    },
    "lmo": {
        "n": 2
    },
    "lnu": {
        "t": 6
    },
    "loc": {
        "y": 1
    },
    "lon": {
        "s": 1
    },
    "lot": {
        "u": 1
    },
    "low": {
        "e": 1,
        "w": 1
    },
    "lup": {
        "i": 1
    },
    "lve": {
        "t": 1
    },
    "mac": {
        "a": 1
    },
    "mai": {
        "z": 1
    },
    "mal": {
        "a": 3
    },
    "mam": {
        "o": 1
    },
    "mar": {
        "a": 1
    },
    "mbe": {
        "a": 1
    },
    "mel": {
        "o": 1
    },
    "mer": {
        "s": 1
    },
    "mil": {
        "l": 1
    },
    "mmo": {
        "n": 1
    },
    "mnu": {
        "t": 1
    },
    "mon": {
        "b": 1,
        "c": 1,
        "d": 2,
        "g": 1,
        "k": 1
    },
    "mor": {
        "i": 1
    },
    "mpe": {
        "d": 1
    },
    "nam": {
        "a": 1
    },
    "nbe": {
        "a": 1,
        "e": 1
    },
    "nci": {
        "l": 1
    },
    "ndi": {
        "a": 1
    },
    "ndl": {
        "e": 1
    },
    "ndn": {
        "u": 2
    },
    "nen": {
        "u": 1
    },
    "nes": {
        "e": 2
    },
    "nfl": {
        "o": 1
    },
    "nge": {
        "d": 1
    },
    "ngo": {
        "n": 1
    },
    "nha": {
        "z": 1
    },
    "nke": {
        "y": 1
    },
    "nnu": {
        "t": 1
    },
    "npe": {
        "a": 1
    },
    "nse": {
        "e": 1
    },
    "nth": {
        "b": 1
    },
    "nut": {
        "s": 6
    },
    "nya": {
        "n": 1
    },
    "oab": {
        "e": 1
    },
    "oad": {
        "b": 1
    },
    "oat": {
        "s": 1
    },
    "oco": {
        "a": 1,
        "n": 1
    },
    "ocy": {
        "n": 1
    },
    "off": {
        "e": 1
    },
    "ogb": {
        "o": 1
    },
    "ola": {
        "n": 1
    },
    "olo": {
        "c": 1
    },
    "omm": {
        "o": 1
    },
    "onb": {
        "e": 1
    },
    "onc": {
        "i": 1
    },
    "ong": {
        "o": 2
    },
    "oni": {
        "o": 1
    },
    "onk": {
        "e": 1
    },
    "onn": {
        "u": 1
    },
    "onp": {
        "e": 1
    },
    "ons": {
        "e": 1
    },
    "onu": {
        "t": 1
    },
    "opp": {
        "l": 1,
        "y": 1
    },
    "org": {
        "h": 1
    },
    "ori": {
        "n": 1
    },
    "otu": {
        "s": 1
    },
    "oun": {
        "d": 2
    },
    "our": {
        "d": 1
    },
    "owe": {
        "r": 1
    },
    "owp": {
        "e": 1
    },
    "oww": {
        "a": 1
    },
    "oxn": {
        "u": 1
    },
    "oyb": {
        "e": 1
    },
    "pal": {
        "m": 2
    },
    "pan": {
        "e": 1
    },
    "par": {
        "a": 1
    },
    "pea": {
        "n": 1,
        "r": 1,
        "s": 1
    },
    "pec": {
        "a": 1
    },
    "ped": {
        "a": 1
    },
    "pel": {
        "t": 1
    },
    "pep": {
        "i": 1
    },
    "pig": {
        "e": 1
    },
    "pil": {
        "i": 2
    },
    "pin": {
        "e": 1
    },
    "pis": {
        "t": 1
    },
    "pit": {
        "a": 1,
        "s": 1
    },
    "ple": {
        "n": 1
    },
    "pop": {
        "p": 1
    },
    "ppl": {
        "e": 1
    },
    "ppy": {
        "s": 1
    },
    "pri": {
        "c": 1
    },
    "puz": {
        "z": 1
    },
    "pys": {
        "e": 1
    },
    "qui": {
        "n": 1
    },
    "rad": {
        "i": 1
    },
    "rai": {
        "n": 1
    },
    "ral": {
        "m": 1
    },
    "ran": {
        "t": 1
    },
    "ras": {
        "s": 1
    },
    "raz": {
        "i": 1
    },
    "rch": {
        "e": 2
    },
    "rea": {
        "d": 1
    },
    "rgh": {
        "u": 1
    },
    "rgo": {
        "u": 1
    },
    "ria": {
        "n": 1
    },
    "ric": {
        "e": 2,
        "o": 1
    },
    "rin": {
        "g": 1
    },
    "rit": {
        "i": 1
    },
    "rle": {
        "y": 1
    },
    "rlm": {
        "i": 1
    },
    "roa": {
        "d": 1
    },
    "rou": {
        "n": 2
    },
    "rse": {
        "e": 1
    },
    "rsg": {
        "r": 1
    },
    "rtn": {
        "u": 1
    },
    "rui": {
        "t": 1
    },
    "ryb": {
        "e": 1
    },
    "sam": {
        "e": 1
    },
    "sec": {
        "h": 2
    },
    "see": {
        "d": 5
    },
    "sen": {
        "u": 1
    },
    "ses": {
        "a": 1
    },
    "sgr": {
        "a": 1
    },
    "sha": {
        "g": 1
    },
    "she": {
        "w": 2
    },
    "sor": {
        "g": 1
    },
    "soy": {
        "b": 1
    },
    "spe": {
        "l": 1
    },
    "sse": {
        "e": 1
    },
    "sta": {
        "c": 1
    },
    "stn": {
        "u": 6
    },
    "sun": {
        "f": 1
    },
    "swe": {
        "e": 1
    },
    "tac": {
        "h": 1
    },
    "tai": {
        "l": 1
    },
    "tbe": {
        "a": 1
    },
    "tch": {
        "e": 1
    },
    "tef": {
        "f": 1
    },
    "ter": {
        "c": 1
    },
    "thb": {
        "e": 1
    },
    "tic": {
        "a": 1
    },
    "tnu": {
        "t": 7
    },
    "tri": {
        "t": 1
    },
    "tse": {
        "e": 1
    },
    "tta": {
        "i": 1
    },
    "tus": {
        "s": 1
    },
    "uck": {
        "w": 1
    },
    "uin": {
        "o": 1
    },
    "und": {
        "n": 2
    },
    "unf": {
        "l": 1
    },
    "uny": {
        "a": 1
    },
    "upi": {
        "n": 1
    },
    "uri": {
        "a": 1
    },
    "uss": {
        "e": 1
    },
    "uzz": {
        "l": 1
    },
    "vab": {
        "e": 1
    },
    "vel": {
        "v": 1
    },
    "vet": {
        "b": 1
    },
    "wal": {
        "n": 3
    },
    "wat": {
        "e": 1
    },
    "wee": {
        "t": 1
    },
    "wer": {
        "s": 1
    },
    "whe": {
        "a": 2
    },
    "wil": {
        "d": 1
    },
    "win": {
        "g": 1
    },
    "wnu": {
        "t": 1
    },
    "wpe": {
        "a": 1
    },
    "wwa": {
        "l": 1
    },
    "xnu": {
        "t": 1
    },
    "yac": {
        "i": 1
    },
    "yam": {
        "b": 1
    },
    "yan": {
        "u": 1
    },
    "ybe": {
        "a": 2
    },
    "yed": {
        "p": 1
    },
    "yel": {
        "l": 1
    },
    "ynt": {
        "h": 1
    },
    "ypu": {
        "z": 1
    },
    "yse": {
        "e": 1
    },
    "zel": {
        "n": 2
    },
    "zil": {
        "n": 1
    },
    "zle": {
        "n": 1
    },
    "zzl": {
        "e": 1
    }
}