{
    "Aeg": {
        "i": 1
    },
    "Ama": {
        "u": 1
    },
    "Aro": {
        "m": 1
    },
    "Aur": {
        "o": 1
    },
    "Ava": {
        "l": 1
    },
    "Bar": {
        "b": 1
    },
    "Ber": {
        "g": 1
    },
    "Bin": {
        "a": 1
    },
    "Bra": {
        "i": 1
    },
    "Bun": {
        "n": 1
    },
    "Car": {
        "b": 1
    },
    "Che": {
        "s": 2
    },
    "Cla": {
        "u": 1,
        "w": 1
    },
    "Ded": {
        "e": 1
    },
    "Del": {
        "p": 1
    },
    "Dia": {
        "n": 1
    },
    "Dig": {
        "g": 1
    },
    "Dou": {
        "b": 1
    },
    "Dra": {
        "g": 1
    },
    "Esp": {
        "u": 1
    },
    "Fen": {
        "n": 1
    },
    "Fla": {
        "b": 1
    },
    "Fle": {
        "t": 2
    },
    "Flo": {
        "e": 1,
        "r": 1
    },
    "Fro": {
        "a": 1,
        "g": 1
    },
    "Fur": {
        "f": 1
    },
    "Gog": {
        "o": 1
    },
    "Goo": {
        "d": 1,
        "m": 1
    },
    "Gou": {
        "r": 1
    },
    "Gre": {
        "n": 1
    },
    "Haw": {
        "l": 1
    },
    "Hel": {
        "i": 2
    },
    "Hon": {
        "e": 1
    },
    "Hoo": {
        "p": 1
    },
    "Ink": {
        "a": 1
    },
    "Kle": {
        "f": 1
    },
    "Lit": {
        "l": 1
    },
    "Mal": {
        "a": 1
    },
    "Meo": {
        "w": 1
    },
    "Noi": {
        "b": 1,
        "v": 1
    },
    "Pan": {
        "c": 1,
        "g": 1
    },
    "Pha": {
        "n": 1
    },
    "Pum": {
        "p": 1
    },
    "Pyr": {
        "o": 1
    },
    "Qui": {
        "l": 1
    },
    "Sca": {
        "t": 1
    },
    "Ski": {
        "d": 1
    },
    "Skr": {
        "e": 1
    },
    "Sli": {
        "g": 1
    },
    "Slu": {
        "r": 1
    },
    "Spe": {
        "w": 1
    },
    "Spr": {
        "i": 1
    },
    "Swi": {
        "r": 1
    },
    "Syl": {
        "v": 1
    },
    "Tal": {
        "o": 1
    },
    "Tre": {
        "v": 1
    },
    "Tyr": {
        "a": 1,
        "u": 1
    },
    "Viv": {
        "i": 1
    },
    "Vol": {
        "c": 1
    },
    "Xer": {
        "n": 1
    },
    "Yve": {
        "l": 1
    },
    "Zyg": {
        "a": 1
    },
    "abo": {
        "o": 1
    },
    "ab\u00e9": {
        "b": 1
    },
    "acl": {
        "e": 2
    },
    "adi": {
        "e": 1,
        "n": 1
    },
    "aga": {
        "l": 1
    },
    "aix": {
        "e": 1
    },
    "aki": {
        "e": 1
    },
    "ala": {
        "m": 1
    },
    "alg": {
        "e": 1
    },
    "alo": {
        "n": 1
    },
    "alu": {
        "g": 1
    },
    "ama": {
        "r": 1
    },
    "anc": {
        "h": 1,
        "i": 1
    },
    "ang": {
        "o": 1
    },
    "ani": {
        "o": 1
    },
    "ant": {
        "r": 1,
        "u": 1
    },
    "ara": {
        "c": 1
    },
    "arb": {
        "a": 1,
        "i": 1
    },
    "ard": {
        "e": 1
    },
    "ati": {
        "s": 1
    },
    "att": {
        "e": 1
    },
    "aug": {
        "h": 1
    },
    "aun": {
        "c": 1
    },
    "aur": {
        "a": 1
    },
    "awi": {
        "t": 1
    },
    "awl": {
        "u": 1
    },
    "bar": {
        "a": 1
    },
    "bin": {
        "k": 1
    },
    "bla": {
        "d": 1
    },
    "b\u00e9b": {
        "\u00e9": 1
    },
    "can": {
        "i": 1
    },
    "cat": {
        "t": 1
    },
    "cha": {
        "m": 1
    },
    "che": {
        "r": 1
    },
    "chi": {
        "n": 1
    },
    "chl": {
        "i": 1
    },
    "den": {
        "n": 1
    },
    "die": {
        "r": 1
    },
    "ede": {
        "n": 1
    },
    "edg": {
        "e": 1
    },
    "efk": {
        "i": 1
    },
    "egi": {
        "s": 1
    },
    "eis": {
        "t": 1
    },
    "eki": {
        "n": 1
    },
    "elb": {
        "y": 1
    },
    "eli": {
        "o": 2
    },
    "elp": {
        "h": 1
    },
    "elt": {
        "a": 1
    },
    "ena": {
        "n": 1
    },
    "eni": {
        "n": 1
    },
    "enn": {
        "e": 2
    },
    "eow": {
        "s": 1
    },
    "erb": {
        "u": 1
    },
    "erg": {
        "m": 1
    },
    "ern": {
        "e": 1
    },
    "ers": {
        "b": 1
    },
    "esn": {
        "a": 1
    },
    "esp": {
        "i": 1
    },
    "etc": {
        "h": 2
    },
    "ett": {
        "e": 1
    },
    "eve": {
        "n": 1
    },
    "ewp": {
        "a": 1
    },
    "fla": {
        "m": 1
    },
    "fro": {
        "u": 1
    },
    "gad": {
        "i": 1
    },
    "gal": {
        "g": 1
    },
    "gar": {
        "d": 1
    },
    "gei": {
        "s": 1
    },
    "ger": {
        "s": 1
    },
    "gge": {
        "r": 1
    },
    "ggo": {
        "o": 1
    },
    "gis": {
        "l": 1
    },
    "gmi": {
        "t": 1
    },
    "goa": {
        "t": 1
    },
    "gor": {
        "o": 1
    },
    "han": {
        "t": 1
    },
    "hes": {
        "n": 1,
        "p": 1
    },
    "hin": {
        "d": 1
    },
    "hli": {
        "n": 1
    },
    "ian": {
        "c": 1
    },
    "iba": {
        "t": 1
    },
    "idd": {
        "o": 1
    },
    "igg": {
        "e": 1,
        "o": 1
    },
    "ill": {
        "a": 1,
        "o": 1
    },
    "ina": {
        "c": 1
    },
    "ind": {
        "e": 1
    },
    "inj": {
        "a": 1
    },
    "iol": {
        "i": 1
    },
    "iop": {
        "t": 1
    },
    "irl": {
        "i": 1
    },
    "isl": {
        "a": 1
    },
    "iss": {
        "e": 1
    },
    "itl": {
        "e": 1
    },
    "itz": {
        "e": 2
    },
    "ive": {
        "r": 1
    },
    "ivi": {
        "l": 1
    },
    "ixe": {
        "n": 1
    },
    "kab": {
        "o": 1
    },
    "kid": {
        "d": 1
    },
    "kre": {
        "l": 1
    },
    "lab": {
        "\u00e9": 1
    },
    "lad": {
        "e": 1,
        "i": 1
    },
    "lam": {
        "a": 1,
        "e": 1
    },
    "las": {
        "h": 1
    },
    "lau": {
        "n": 1
    },
    "law": {
        "i": 1
    },
    "lca": {
        "n": 1
    },
    "lef": {
        "k": 1
    },
    "let": {
        "c": 2
    },
    "lig": {
        "g": 1
    },
    "lin": {
        "g": 1
    },
    "lio": {
        "l": 1,
        "p": 1
    },
    "lis": {
        "k": 1
    },
    "lla": {
        "d": 1
    },
    "llo": {
        "n": 1
    },
    "loe": {
        "t": 1
    },
    "lon": {
        "f": 1
    },
    "lor": {
        "g": 1
    },
    "lph": {
        "o": 1
    },
    "lta": {
        "l": 1
    },
    "luc": {
        "h": 1
    },
    "lug": {
        "g": 1
    },
    "lur": {
        "p": 1
    },
    "lve": {
        "o": 1
    },
    "mat": {
        "i": 1
    },
    "mau": {
        "r": 1
    },
    "mit": {
        "e": 1
    },
    "mpk": {
        "a": 1
    },
    "nac": {
        "l": 1
    },
    "nan": {
        "t": 1
    },
    "nau": {
        "g": 1
    },
    "nch": {
        "a": 1,
        "e": 1
    },
    "nci": {
        "e": 1
    },
    "nde": {
        "r": 1
    },
    "nea": {
        "s": 1
    },
    "ned": {
        "g": 1
    },
    "nek": {
        "i": 1
    },
    "nel": {
        "b": 1
    },
    "nfl": {
        "a": 1
    },
    "ngo": {
        "r": 1
    },
    "nin": {
        "j": 1
    },
    "nio": {
        "n": 1
    },
    "nka": {
        "y": 1
    },
    "nne": {
        "k": 1,
        "l": 1
    },
    "ntr": {
        "u": 1
    },
    "ntu": {
        "m": 1
    },
    "oak": {
        "i": 1
    },
    "odr": {
        "a": 1
    },
    "oet": {
        "t": 1
    },
    "oga": {
        "d": 1
    },
    "ogo": {
        "a": 1
    },
    "oib": {
        "a": 1
    },
    "oiv": {
        "e": 1
    },
    "olc": {
        "a": 1
    },
    "oli": {
        "s": 1
    },
    "oma": {
        "t": 1
    },
    "one": {
        "d": 1
    },
    "onf": {
        "l": 1
    },
    "ood": {
        "r": 1
    },
    "oom": {
        "y": 1
    },
    "oop": {
        "a": 1
    },
    "opt": {
        "i": 1
    },
    "org": {
        "e": 1
    },
    "oru": {
        "s": 1
    },
    "oub": {
        "l": 1
    },
    "our": {
        "g": 1
    },
    "ows": {
        "t": 1
    },
    "pew": {
        "p": 1
    },
    "pho": {
        "x": 1
    },
    "pka": {
        "b": 1
    },
    "pri": {
        "t": 1
    },
    "pti": {
        "l": 1
    },
    "puf": {
        "f": 1
    },
    "pur": {
        "r": 1
    },
    "rac": {
        "l": 1
    },
    "rag": {
        "a": 1
    },
    "rai": {
        "x": 1
    },
    "ran": {
        "t": 1
    },
    "rba": {
        "r": 1
    },
    "rbi": {
        "n": 1
    },
    "rbu": {
        "g": 1
    },
    "rel": {
        "p": 1
    },
    "ren": {
        "i": 1
    },
    "rev": {
        "e": 1
    },
    "rfr": {
        "o": 1
    },
    "rge": {
        "i": 1,
        "s": 1
    },
    "rgm": {
        "i": 1
    },
    "rit": {
        "z": 1
    },
    "rli": {
        "x": 1
    },
    "rne": {
        "a": 1
    },
    "roa": {
        "k": 1,
        "r": 1
    },
    "rog": {
        "a": 1
    },
    "rom": {
        "a": 1
    },
    "ror": {
        "u": 1
    },
    "rpu": {
        "f": 1
    },
    "rsb": {
        "y": 1
    },
    "run": {
        "t": 1
    },
    "sla": {
        "s": 1
    },
    "sna": {
        "u": 1
    },
    "spi": {
        "n": 1
    },
    "spu": {
        "r": 1
    },
    "sti": {
        "c": 1
    },
    "tch": {
        "i": 1,
        "l": 1
    },
    "ter": {
        "b": 1
    },
    "til": {
        "e": 1
    },
    "tis": {
        "s": 1
    },
    "tle": {
        "o": 1
    },
    "tru": {
        "m": 1
    },
    "tte": {
        "r": 1
    },
    "tum": {
        "p": 1
    },
    "tze": {
        "e": 1,
        "r": 1
    },
    "ubl": {
        "a": 1
    },
    "uch": {
        "a": 1
    },
    "ugh": {
        "t": 1
    },
    "uil": {
        "l": 1
    },
    "ump": {
        "k": 1
    },
    "unc": {
        "h": 1
    },
    "unn": {
        "e": 1
    },
    "urf": {
        "r": 1
    },
    "urg": {
        "e": 1
    },
    "uro": {
        "r": 1
    },
    "urp": {
        "u": 1
    },
    "val": {
        "u": 1
    },
    "vel": {
        "t": 1
    },
    "ven": {
        "a": 1
    },
    "veo": {
        "n": 1
    },
    "ver": {
        "n": 1
    },
    "vil": {
        "l": 1
    },
    "wir": {
        "l": 1
    },
    "wit": {
        "z": 1
    },
    "wlu": {
        "c": 1
    },
    "wst": {
        "i": 1
    },
    "yga": {
        "r": 1
    },
    "ylv": {
        "e": 1
    },
    "yra": {
        "n": 1
    },
    "yro": {
        "a": 1
    },
    "yru": {
        "n": 1
    }
}