{
    "  D": {
        "u": 1
    },
    "  H": {
        "e": 1
    },
    "  p": {
        "y": 1
    },
    " Ad": {
        "a": 2
    },
    " Ai": {
        "l": 1
    },
    " At": {
        "o": 2
    },
    " Ba": {
        "u": 1,
        "y": 1
    },
    " Ca": {
        "v": 1
    },
    " Ch": {
        "r": 1
    },
    " Du": {
        "c": 2
    },
    " Ea": {
        "s": 1
    },
    " Ha": {
        "r": 3
    },
    " He": {
        "n": 6
    },
    " Hi": {
        "l": 1
    },
    " Ho": {
        "l": 1
    },
    " In": {
        "s": 1
    },
    " Is": {
        "l": 15
    },
    " Ju": {
        "a": 1
    },
    " Ma": {
        "r": 1
    },
    " Mi": {
        "l": 1
    },
    " Oe": {
        "n": 2
    },
    " Pa": {
        "u": 5
    },
    " Pi": {
        "k": 2,
        "t": 18
    },
    " Pl": {
        "a": 1
    },
    " Po": {
        "i": 6
    },
    " Re": {
        "s": 1
    },
    " Ri": {
        "d": 3
    },
    " Ro": {
        "c": 2,
        "p": 1
    },
    " Si": {
        "d": 1
    },
    " To": {
        "w": 1
    },
    " Va": {
        "l": 7
    },
    " an": {
        "d": 2
    },
    " ay": {
        "s": 1
    },
    " by": {
        "t": 1
    },
    " da": {
        "n": 1,
        "o": 5
    },
    " de": {
        " ": 1
    },
    " du": {
        "i": 1
    },
    " en": {
        " ": 1
    },
    " ga": {
        "o": 1
    },
    " je": {
        "d": 1
    },
    " ka": {
        "i": 1
    },
    " ma": {
        "r": 1
    },
    " nu": {
        "t": 1
    },
    " os": {
        "t": 3
    },
    " ot": {
        "o": 1
    },
    " py": {
        "t": 1
    },
    " qu": {
        "n": 1
    },
    " sa": {
        "l": 1
    },
    " si": {
        " ": 1
    },
    " te": {
        " ": 1
    },
    " uh": {
        "a": 1
    },
    " zh": {
        "u": 1
    },
    " \u0111\u1ea3": {
        "o": 1
    },
    " \u0192u": {
        "d": 1
    },
    " \u03a0\u03af": {
        "\u03c4": 1
    },
    " \u041f\u0438": {
        "\u0442": 2
    },
    " \u041f\u0456": {
        "\u0442": 1
    },
    " \u043e\u0441": {
        "\u0442": 1
    },
    " \u0627\u06cc": {
        "\u0633": 1
    },
    " \u0628\u064a": {
        "\u062a": 1
    },
    " \u062c\u0632": {
        "\u0627": 2
    },
    " \u0679\u0627": {
        "\u0624": 1
    },
    " \u067e\u0679": {
        "\u06a9": 1
    },
    " \u067e\u06cc": {
        "\u062a": 2
    },
    " \u0daf\u0dd6": {
        "\u0db4": 1
    },
    "'Ot": {
        "u": 1
    },
    "'ir": {
        "i": 1,
        "n": 1
    },
    "'ki": {
        " ": 1
    },
    "'s ": {
        "I": 1
    },
    ", D": {
        "u": 1
    },
    ", H": {
        "e": 1
    },
    "-Pi": {
        "t": 1
    },
    "-sz": {
        "i": 2
    },
    "Ada": {
        "m": 7,
        "s": 2
    },
    "Ail": {
        "e": 1
    },
    "Ant": {
        "a": 1
    },
    "Ato": {
        "l": 2
    },
    "Awa": {
        "h": 1
    },
    "Bau": {
        "t": 1
    },
    "Ben": {
        "s": 1
    },
    "Bou": {
        "n": 1
    },
    "Cav": {
        "e": 1
    },
    "Chr": {
        "i": 2
    },
    "Coy": {
        "s": 1
    },
    "Dee": {
        "p": 1
    },
    "Duc": {
        "i": 5
    },
    "Eas": {
        "t": 1
    },
    "Eli": {
        "z": 1
    },
    "Ene": {
        "z": 1
    },
    "Gar": {
        "n": 1
    },
    "Gen": {
        "s": 1
    },
    "Gud": {
        "g": 2
    },
    "Har": {
        "b": 3
    },
    "Hen": {
        "d": 9
    },
    "Hil": {
        "l": 1
    },
    "Hol": {
        "l": 2
    },
    "Ile": {
        " ": 1,
        "s": 1
    },
    "Ilh": {
        "a": 1
    },
    "Ill": {
        "a": 1,
        "e": 1
    },
    "Ins": {
        "u": 2
    },
    "Isl": {
        "a": 16,
        "e": 1
    },
    "Iso": {
        "l": 1
    },
    "Joh": {
        "n": 1
    },
    "Jua": {
        "n": 1
    },
    "Kep": {
        "u": 1
    },
    "Kun": {
        "d": 1
    },
    "Lon": {
        "g": 1
    },
    "Loo": {
        "k": 1
    },
    "Man": {
        "e": 1
    },
    "Mar": {
        "i": 1
    },
    "McC": {
        "o": 1
    },
    "Mid": {
        "d": 1
    },
    "Mil": {
        "l": 1
    },
    "Nes": {
        "o": 1
    },
    "Nor": {
        "t": 1
    },
    "Occ": {
        "a": 1
    },
    "Oen": {
        "o": 5
    },
    "Ori": {
        "l": 1
    },
    "Or\u00ed": {
        "l": 1
    },
    "Ost": {
        "r": 3
    },
    "Otu": {
        "m": 2
    },
    "Out": {
        "e": 1
    },
    "Par": {
        "l": 1
    },
    "Pau": {
        "l": 5
    },
    "Pik": {
        "a": 3
    },
    "Pit": {
        "a": 1,
        "c": 34,
        "i": 7,
        "k": 18
    },
    "Pla": {
        "c": 1
    },
    "Poi": {
        "n": 7
    },
    "Qua": {
        "n": 1
    },
    "Qu\u1ea7": {
        "n": 1
    },
    "Res": {
        "e": 1
    },
    "Rid": {
        "g": 3
    },
    "Roc": {
        "k": 2
    },
    "Rop": {
        "e": 1
    },
    "Sai": {
        "n": 5
    },
    "San": {
        " ": 1,
        "d": 2
    },
    "Sid": {
        "e": 1
    },
    "Sou": {
        "t": 1
    },
    "Tah": {
        "o": 2
    },
    "Ted": {
        " ": 1
    },
    "The": {
        " ": 2
    },
    "Tow": {
        "n": 1
    },
    "Val": {
        "l": 7
    },
    "Wat": {
        "e": 1
    },
    "Wes": {
        "t": 1
    },
    "Yny": {
        "s": 1
    },
    "You": {
        "n": 1
    },
    "a H": {
        "e": 2
    },
    "a I": {
        "n": 1
    },
    "a P": {
        "i": 2
    },
    "a d": {
        "a": 1,
        "e": 1
    },
    "a'i": {
        "r": 2
    },
    "abe": {
        "t": 1
    },
    "ada": {
        "m": 1
    },
    "adm": {
        "z": 2
    },
    "aed": {
        "e": 1
    },
    "aho": {
        "u": 3
    },
    "ai ": {
        "e": 1
    },
    "ain": {
        "t": 5
    },
    "air": {
        "n": 40
    },
    "ajr": {
        "n": 1
    },
    "aka": {
        "'": 2,
        "i": 1,
        "r": 1
    },
    "ake": {
        "y": 1
    },
    "all": {
        "e": 7
    },
    "alo": {
        "s": 1
    },
    "ams": {
        " ": 2,
        "t": 7
    },
    "amu": {
        "s": 1
    },
    "an ": {
        "B": 1,
        "J": 1,
        "P": 1,
        "d": 1,
        "g": 1,
        "z": 1
    },
    "and": {
        " ": 2,
        "e": 2,
        "s": 6,
        "y": 2
    },
    "ane": {
        "l": 1
    },
    "ang": {
        " ": 1
    },
    "ans": {
        " ": 1
    },
    "ao ": {
        "P": 1
    },
    "aou": {
        "n": 1
    },
    "arb": {
        "o": 3
    },
    "ari": {
        "n": 5
    },
    "arl": {
        "v": 1
    },
    "arn": {
        "a": 4,
        "e": 1
    },
    "arq": {
        "a": 1
    },
    "art": {
        "e": 1
    },
    "as ": {
        "I": 1,
        "P": 1
    },
    "aso": {
        "n": 1
    },
    "ast": {
        " ": 1
    },
    "ata": {
        "m": 1
    },
    "ate": {
        "r": 1
    },
    "aua": {
        "n": 1
    },
    "aul": {
        " ": 1,
        "'": 1,
        "s": 2,
        "\u2019": 1
    },
    "aun": {
        "a": 1,
        "o": 1
    },
    "aut": {
        "i": 1
    },
    "avu": {
        "n": 1
    },
    "ays": {
        "l": 1
    },
    "a\u016dn": {
        "o": 1
    },
    "bet": {
        "h": 1
    },
    "bou": {
        "r": 1
    },
    "byt": {
        "k": 1
    },
    "cCo": {
        "y": 1
    },
    "cai": {
        "r": 34
    },
    "cas": {
        " ": 1
    },
    "cca": {
        "s": 1
    },
    "cie": {
        " ": 4
    },
    "d O": {
        "e": 2
    },
    "d S": {
        "i": 1
    },
    "dam": {
        "s": 7,
        "u": 1
    },
    "dan": {
        "g": 1
    },
    "das": {
        "i": 1,
        "o": 1,
        "\u0131": 1
    },
    "ddl": {
        "e": 1
    },
    "de ": {
        "P": 3
    },
    "deo": {
        "m": 1
    },
    "der": {
        "s": 9
    },
    "dge": {
        "e": 1,
        "o": 1
    },
    "dle": {
        " ": 1
    },
    "dmz": {
        "t": 2
    },
    "dom": {
        "e": 1
    },
    "ds ": {
        "M": 1
    },
    "dur": {
        " ": 1
    },
    "dy ": {
        "I": 2
    },
    "e A": {
        "t": 1
    },
    "e H": {
        "e": 2,
        "i": 1,
        "o": 1
    },
    "e I": {
        "s": 1
    },
    "e P": {
        "i": 5
    },
    "e R": {
        "e": 1,
        "o": 1
    },
    "e V": {
        "a": 1
    },
    "e a": {
        "n": 2
    },
    "e k": {
        "a": 1
    },
    "e o": {
        "s": 1
    },
    "ean": {
        " ": 2
    },
    "ear": {
        "n": 1
    },
    "ed ": {
        "S": 1
    },
    "ede": {
        " ": 1,
        "o": 1
    },
    "eed": {
        "e": 1
    },
    "een": {
        "i": 1
    },
    "eeo": {
        "n": 2
    },
    "eep": {
        " ": 1
    },
    "ehr": {
        "n": 2
    },
    "eil": {
        "a": 1
    },
    "ekp": {
        "o": 1
    },
    "ele": {
        " ": 1,
        "e": 1
    },
    "en ": {
        "q": 1
    },
    "end": {
        "a": 1,
        "e": 9
    },
    "eno": {
        " ": 5
    },
    "ens": {
        " ": 1,
        "e": 1
    },
    "eom": {
        "s": 1
    },
    "eon": {
        " ": 2,
        "s": 1
    },
    "ep ": {
        "V": 1
    },
    "epu": {
        "l": 1
    },
    "er ": {
        "V": 3
    },
    "ern": {
        " ": 2,
        "a": 2,
        "i": 1,
        "o": 1,
        "s": 1
    },
    "ers": {
        "o": 9
    },
    "erv": {
        "e": 1
    },
    "es ": {
        "P": 3
    },
    "ese": {
        "r": 1
    },
    "eso": {
        "i": 1
    },
    "est": {
        "e": 1
    },
    "ete": {
        "k": 1
    },
    "eth": {
        " ": 1
    },
    "ets": {
        " ": 1
    },
    "eut": {
        "a": 1
    },
    "ey ": {
        "R": 1
    },
    "eya": {
        "r": 1
    },
    "eyi": {
        "r": 1
    },
    "eyr": {
        "n": 1
    },
    "ez ": {
        "P": 1
    },
    "g R": {
        "i": 1
    },
    "g s": {
        "i": 1
    },
    "gao": {
        " ": 1
    },
    "gee": {
        "n": 1
    },
    "geo": {
        "n": 1
    },
    "get": {
        "e": 1
    },
    "gs ": {
        "R": 1
    },
    "h E": {
        "a": 1
    },
    "h I": {
        "s": 1
    },
    "h P": {
        "o": 1
    },
    "ha ": {
        "H": 1
    },
    "har": {
        "t": 1
    },
    "he ": {
        "H": 1,
        "R": 1
    },
    "hen": {
        "d": 1
    },
    "hn ": {
        "M": 1
    },
    "hou": {
        " ": 1,
        "t": 2
    },
    "hri": {
        "s": 2
    },
    "hu ": {
        "d": 1
    },
    "i P": {
        "i": 2
    },
    "i d": {
        "u": 1
    },
    "i e": {
        "n": 1
    },
    "i o": {
        "s": 1,
        "t": 1
    },
    "i t": {
        "e": 1
    },
    "i-P": {
        "i": 1
    },
    "ian": {
        "s": 1
    },
    "idd": {
        "l": 1
    },
    "idg": {
        "e": 3
    },
    "ie ": {
        "A": 1,
        "I": 1,
        "a": 2
    },
    "ige": {
        "t": 2
    },
    "ika": {
        "i": 1,
        "r": 3
    },
    "ike": {
        "e": 1,
        "n": 2,
        "r": 1,
        "y": 1
    },
    "ik\u00ea": {
        "r": 1
    },
    "ila": {
        "n": 1
    },
    "ile": {
        "e": 1,
        "n": 1
    },
    "ill": {
        "s": 1
    },
    "ine": {
        " ": 1
    },
    "ins": {
        "e": 1
    },
    "int": {
        " ": 6
    },
    "iri": {
        "n": 2
    },
    "irn": {
        " ": 9,
        "'": 1,
        ",": 1,
        "-": 1,
        "a": 2,
        "e": 1,
        "i": 3,
        "o": 4,
        "s": 1,
        "\u00f6": 1,
        "\u00f8": 1,
        "\u2019": 1
    },
    "isk": {
        "e": 2
    },
    "ist": {
        "a": 1,
        "i": 2
    },
    "ita": {
        "k": 5
    },
    "itc": {
        "a": 34
    },
    "iti": {
        "k": 7
    },
    "itk": {
        "a": 7,
        "e": 12,
        "\u0113": 1
    },
    "ito": {
        "k": 2
    },
    "iza": {
        "b": 1
    },
    "jed": {
        "o": 1
    },
    "jzr": {
        " ": 1
    },
    "ka'": {
        "i": 2
    },
    "kai": {
        " ": 1,
        "r": 6
    },
    "kaj": {
        "r": 1
    },
    "kar": {
        "i": 4,
        "n": 2
    },
    "kea": {
        "n": 2
    },
    "kee": {
        "n": 1,
        "o": 2
    },
    "keh": {
        "r": 2
    },
    "ken": {
        "i": 2
    },
    "ker": {
        "n": 10
    },
    "key": {
        "a": 1,
        "i": 1,
        "r": 1
    },
    "ki ": {
        "o": 2
    },
    "kou": {
        "t": 1
    },
    "kpo": {
        " ": 1
    },
    "krn": {
        " ": 1
    },
    "kyr": {
        "n": 1
    },
    "k\u00ear": {
        "n": 1
    },
    "k\u0113r": {
        "n": 1
    },
    "l P": {
        "o": 1
    },
    "la ": {
        "H": 1,
        "d": 1
    },
    "lac": {
        "e": 1
    },
    "lan": {
        "d": 15
    },
    "las": {
        " ": 1
    },
    "lau": {
        "a": 1
    },
    "le ": {
        "H": 3,
        "P": 2
    },
    "lee": {
        "d": 1
    },
    "lel": {
        "e": 1
    },
    "les": {
        " ": 3
    },
    "let": {
        "s": 1
    },
    "ley": {
        " ": 1
    },
    "lha": {
        " ": 1
    },
    "liz": {
        "a": 1
    },
    "lla": {
        " ": 1
    },
    "lle": {
        "s": 1,
        "y": 7
    },
    "llo": {
        "w": 1
    },
    "lls": {
        " ": 1
    },
    "lly": {
        "a": 1
    },
    "ls ": {
        "H": 1,
        "P": 1,
        "V": 1
    },
    "lve": {
        "r": 1
    },
    "lya": {
        "n": 1
    },
    "l\u1eb9\u0301": {
        "\u00e8": 1
    },
    "mar": {
        "q": 1
    },
    "mek": {
        "p": 1
    },
    "mot": {
        "u": 2
    },
    "ms ": {
        "R": 1,
        "T": 1
    },
    "mse": {
        "u": 1
    },
    "mst": {
        "a": 6,
        "o": 1
    },
    "mus": {
        "u": 1
    },
    "mzt": {
        "a": 1,
        "w": 1
    },
    "n  ": {
        "D": 1,
        "H": 1,
        "p": 1
    },
    "n A": {
        "d": 2,
        "i": 1
    },
    "n B": {
        "a": 1
    },
    "n H": {
        "a": 2
    },
    "n I": {
        "s": 5
    },
    "n J": {
        "u": 1
    },
    "n M": {
        "i": 1
    },
    "n P": {
        "i": 1
    },
    "n a": {
        "y": 1
    },
    "n d": {
        "a": 3
    },
    "n g": {
        "a": 1
    },
    "n j": {
        "e": 1
    },
    "n q": {
        "u": 1
    },
    "n u": {
        "h": 1
    },
    "n z": {
        "h": 1
    },
    "n \u0111": {
        "\u1ea3": 1
    },
    "n \u0192": {
        "u": 1
    },
    "n's": {
        " ": 1
    },
    "n, ": {
        "D": 1,
        "H": 1
    },
    "n-s": {
        "z": 2
    },
    "na ": {
        "I": 1
    },
    "nd ": {
        "O": 2
    },
    "nda": {
        "s": 1
    },
    "nde": {
        "n": 1,
        "r": 10
    },
    "nds": {
        " ": 1
    },
    "ndu": {
        "r": 1
    },
    "ndy": {
        " ": 2
    },
    "ne ": {
        "R": 1
    },
    "nei": {
        "l": 1
    },
    "nel": {
        "e": 1
    },
    "net": {
        "s": 1
    },
    "nez": {
        " ": 1
    },
    "ng ": {
        "R": 1,
        "s": 1
    },
    "ngs": {
        " ": 1
    },
    "nin": {
        "s": 1
    },
    "no ": {
        "A": 1,
        "I": 3,
        "d": 1,
        "s": 1
    },
    "noe": {
        "a": 1
    },
    "nov": {
        "e": 1,
        "y": 1
    },
    "noy": {
        "e": 1
    },
    "ns ": {
        "C": 1,
        "P": 1
    },
    "ns'": {
        "k": 1
    },
    "nse": {
        " ": 1,
        "l": 1,
        "o": 1
    },
    "nsk": {
        "i": 1
    },
    "nsu": {
        "l": 2
    },
    "nt ": {
        "C": 1,
        "P": 5
    },
    "nta": {
        "m": 1
    },
    "nty": {
        " ": 1
    },
    "nut": {
        "o": 1
    },
    "nys": {
        "o": 1
    },
    "n\u00f6a": {
        "r": 1
    },
    "n\u00f8y": {
        "e": 1
    },
    "n\u2019s": {
        " ": 1
    },
    "o A": {
        "t": 1
    },
    "o I": {
        "s": 3
    },
    "o P": {
        "i": 2
    },
    "o d": {
        "a": 1
    },
    "o n": {
        "u": 1
    },
    "o s": {
        "a": 1
    },
    "oea": {
        "r": 1
    },
    "oen": {
        "o": 1
    },
    "ohn": {
        " ": 1
    },
    "oi ": {
        "P": 1
    },
    "oin": {
        "t": 7
    },
    "oke": {
        "a": 2
    },
    "oko": {
        "u": 1
    },
    "ole": {
        " ": 1
    },
    "oll": {
        "o": 1,
        "y": 1
    },
    "ome": {
        "k": 1
    },
    "oms": {
        "e": 1
    },
    "on ": {
        " ": 1,
        "H": 1,
        "I": 1,
        "d": 1,
        "j": 1
    },
    "on,": {
        " ": 1
    },
    "on-": {
        "s": 1
    },
    "ong": {
        " ": 1
    },
    "ons": {
        "e": 1
    },
    "ook": {
        "o": 1
    },
    "ort": {
        "h": 1
    },
    "ost": {
        "r": 3
    },
    "oto": {
        "k": 1
    },
    "otu": {
        " ": 2
    },
    "ou ": {
        "P": 1
    },
    "oum": {
        "a": 1
    },
    "oun": {
        "g": 1,
        "t": 1
    },
    "out": {
        " ": 1,
        "h": 1,
        "o": 1,
        "u": 1
    },
    "ova": {
        " ": 1
    },
    "ove": {
        " ": 1
    },
    "ovi": {
        " ": 1
    },
    "ovy": {
        " ": 1
    },
    "ow ": {
        "P": 1
    },
    "oye": {
        "n": 1
    },
    "oys": {
        " ": 1
    },
    "p V": {
        "a": 1
    },
    "pi ": {
        "t": 1
    },
    "pis": {
        "k": 2
    },
    "pit": {
        "a": 4,
        "k": 2,
        "o": 2
    },
    "po ": {
        "n": 1
    },
    "pul": {
        "a": 1
    },
    "pyt": {
        "k": 1,
        "q": 1
    },
    "qun": {
        " ": 1
    },
    "r V": {
        "a": 3
    },
    "r b": {
        "y": 1
    },
    "r m": {
        "a": 1
    },
    "rbo": {
        "r": 2,
        "u": 1
    },
    "ril": {
        "e": 1
    },
    "rin": {
        "e": 1,
        "i": 4
    },
    "ris": {
        "t": 2
    },
    "rlv": {
        "e": 1
    },
    "rn ": {
        " ": 1,
        "A": 3,
        "H": 1,
        "I": 4,
        "a": 1,
        "u": 1,
        "\u0192": 1
    },
    "rn'": {
        "s": 1
    },
    "rn,": {
        " ": 1
    },
    "rn-": {
        "s": 1
    },
    "rna": {
        " ": 1,
        "s": 1
    },
    "rne": {
        "i": 1,
        "t": 1
    },
    "rni": {
        "n": 1
    },
    "rno": {
        " ": 1,
        "e": 1,
        "v": 2,
        "y": 1
    },
    "rns": {
        "'": 1,
        "k": 1
    },
    "rn\u00f6": {
        "a": 1
    },
    "rn\u00f8": {
        "y": 1
    },
    "rn\u2019": {
        "s": 1
    },
    "rov": {
        "a": 1,
        "i": 2,
        "y": 2
    },
    "rso": {
        "n": 9
    },
    "rte": {
        "a": 1
    },
    "rth": {
        " ": 1
    },
    "rva": {
        " ": 1
    },
    "r\u00edl": {
        "\u1eb9": 1
    },
    "s C": {
        "a": 1
    },
    "s H": {
        "a": 1
    },
    "s I": {
        "s": 3
    },
    "s M": {
        "a": 1
    },
    "s P": {
        "i": 4,
        "l": 1,
        "o": 1
    },
    "s R": {
        "i": 1,
        "o": 2
    },
    "s T": {
        "o": 1
    },
    "s V": {
        "a": 2
    },
    "s'k": {
        "i": 1
    },
    "sal": {
        "o": 1
    },
    "se ": {
        "V": 1
    },
    "sel": {
        "n": 1
    },
    "seo": {
        "m": 1
    },
    "ser": {
        "v": 1
    },
    "seu": {
        "t": 1
    },
    "si ": {
        "d": 1
    },
    "ske": {
        "e": 2
    },
    "ski": {
        " ": 1
    },
    "sla": {
        " ": 1,
        "n": 14,
        "s": 1
    },
    "sle": {
        "t": 1
    },
    "sln": {
        "d": 1
    },
    "soi": {
        " ": 1
    },
    "sol": {
        "e": 1
    },
    "son": {
        " ": 3,
        ",": 1,
        "-": 1
    },
    "sow": {
        " ": 1
    },
    "st ": {
        "P": 1
    },
    "sta": {
        "o": 1,
        "u": 3,
        "v": 1,
        "\u016d": 1
    },
    "ste": {
        "r": 1
    },
    "sti": {
        "a": 2
    },
    "sto": {
        "w": 1
    },
    "str": {
        "o": 5,
        "v": 1
    },
    "sul": {
        "e": 1,
        "o": 1
    },
    "sut": {
        "a": 1
    },
    "szi": {
        "g": 2
    },
    "t C": {
        "h": 1
    },
    "t P": {
        "a": 5,
        "o": 2
    },
    "tak": {
        "a": 4,
        "e": 1
    },
    "tam": {
        "s": 2
    },
    "tao": {
        "u": 1
    },
    "tau": {
        "n": 5
    },
    "tav": {
        "u": 1
    },
    "taw": {
        "n": 1
    },
    "ta\u016d": {
        "n": 1
    },
    "tca": {
        "i": 34
    },
    "te ": {
        "k": 1
    },
    "tea": {
        "k": 1
    },
    "ter": {
        " ": 2,
        "n": 1
    },
    "th ": {
        "E": 1,
        "I": 1,
        "P": 1
    },
    "tia": {
        "n": 2
    },
    "tik": {
        "a": 1,
        "e": 5,
        "\u00ea": 1
    },
    "tis": {
        "t": 1
    },
    "tka": {
        "i": 4,
        "j": 1,
        "r": 2
    },
    "tke": {
        "h": 2,
        "r": 9,
        "y": 1
    },
    "tkr": {
        "n": 1
    },
    "tky": {
        "r": 1
    },
    "tk\u0113": {
        "r": 1
    },
    "tok": {
        "e": 2,
        "i": 1
    },
    "tol": {
        "l": 2
    },
    "tom": {
        "e": 1
    },
    "tou": {
        "m": 1
    },
    "tow": {
        "n": 1
    },
    "tqr": {
        "n": 1
    },
    "tro": {
        "v": 5
    },
    "trv": {
        "a": 1
    },
    "ts ": {
        "R": 1
    },
    "tu ": {
        "P": 2
    },
    "tum": {
        "a": 1,
        "o": 2
    },
    "twn": {
        " ": 1
    },
    "ty ": {
        "B": 1
    },
    "u P": {
        "i": 2,
        "o": 1
    },
    "u d": {
        "a": 1
    },
    "uan": {
        " ": 3
    },
    "uci": {
        "e": 5
    },
    "udg": {
        "e": 2
    },
    "udo": {
        "m": 1
    },
    "uha": {
        "r": 1
    },
    "ul ": {
        "P": 1
    },
    "ul'": {
        "s": 1
    },
    "ula": {
        "u": 1
    },
    "ule": {
        "l": 1
    },
    "uls": {
        " ": 2
    },
    "ul\u2019": {
        "s": 1
    },
    "uma": {
        "h": 2
    },
    "umo": {
        "t": 2
    },
    "un ": {
        "d": 1
    },
    "una": {
        "s": 1
    },
    "und": {
        "u": 1
    },
    "ung": {
        "s": 1
    },
    "unt": {
        "y": 1
    },
    "ur ": {
        "m": 1
    },
    "usu": {
        "t": 1
    },
    "ut ": {
        "P": 1
    },
    "uta": {
        "u": 2
    },
    "ute": {
        "r": 1
    },
    "uth": {
        " ": 1
    },
    "uti": {
        "s": 1
    },
    "uto": {
        "m": 1,
        "u": 1
    },
    "utu": {
        "m": 1
    },
    "u\u1ea7n": {
        " ": 1
    },
    "va ": {
        "P": 2
    },
    "ve ": {
        "o": 1
    },
    "ver": {
        " ": 1
    },
    "vi ": {
        "P": 1
    },
    "vy ": {
        "o": 1
    },
    "w P": {
        "i": 1
    },
    "wah": {
        "o": 1
    },
    "wn ": {
        " ": 1
    },
    "y B": {
        "a": 1
    },
    "y I": {
        "s": 2
    },
    "y R": {
        "i": 1
    },
    "y o": {
        "s": 1
    },
    "ya ": {
        "d": 1
    },
    "yan": {
        "d": 1
    },
    "yar": {
        "n": 1
    },
    "yen": {
        "e": 2
    },
    "yir": {
        "i": 1
    },
    "ys ": {
        "V": 1
    },
    "ysl": {
        "n": 1
    },
    "yso": {
        "w": 1
    },
    "ytk": {
        "r": 1,
        "y": 1
    },
    "ytq": {
        "r": 1
    },
    "z P": {
        "i": 1
    },
    "zab": {
        "e": 1
    },
    "zhu": {
        " ": 1
    },
    "zig": {
        "e": 2
    },
    "zr ": {
        "b": 1
    },
    "zta": {
        "w": 1
    },
    "ztw": {
        "n": 1
    },
    "\u00cele": {
        " ": 1,
        "s": 1
    },
    "\u00e8de": {
        " ": 1
    },
    "\u00earn": {
        "i": 1
    },
    "\u00edl\u1eb9": {
        "\u0301": 1
    },
    "\u00f6ar": {
        "n": 1
    },
    "\u00f8ye": {
        "n": 1
    },
    "\u0111\u1ea3o": {
        " ": 1
    },
    "\u0113rn": {
        "a": 1
    },
    "\u0192ud": {
        "o": 1
    },
    "\u02bbOt": {
        "u": 1
    },
    "\u0301\u00e8d": {
        "e": 1
    },
    "\u0386\u03bd\u03c4": {
        "\u03b1": 1
    },
    "\u039d\u03ae\u03c3": {
        "\u03bf": 1
    },
    "\u03a0\u03af\u03c4": {
        "\u03ba": 2
    },
    "\u03ae\u03c3\u03bf": {
        "\u03b9": 1
    },
    "\u03af\u03c4\u03ba": {
        "\u03b1": 1,
        "\u03b5": 1
    },
    "\u03b1\u03b9\u03c1": {
        "\u03bd": 1
    },
    "\u03b1\u03bc\u03c3": {
        "\u03c4": 1
    },
    "\u03b1\u03bf\u03c5": {
        "\u03bd": 1
    },
    "\u03b9 \u03a0": {
        "\u03af": 1
    },
    "\u03ba\u03b1\u03b9": {
        "\u03c1": 1
    },
    "\u03ba\u03b5\u03c1": {
        "\u03bd": 1
    },
    "\u03bc\u03c3\u03c4": {
        "\u03b1": 1
    },
    "\u03bd\u03c4\u03b1": {
        "\u03bc": 1
    },
    "\u03bf\u03b9 ": {
        "\u03a0": 1
    },
    "\u03c3\u03bf\u03b9": {
        " ": 1
    },
    "\u03c3\u03c4\u03b1": {
        "\u03bf": 1
    },
    "\u03c4\u03b1\u03bc": {
        "\u03c3": 1
    },
    "\u03c4\u03b1\u03bf": {
        "\u03c5": 1
    },
    "\u03c4\u03ba\u03b1": {
        "\u03b9": 1
    },
    "\u03c4\u03ba\u03b5": {
        "\u03c1": 1
    },
    "\u0410\u0434\u0430": {
        "\u043c": 2
    },
    "\u041e\u0441\u0442": {
        "\u0440": 3
    },
    "\u041f\u0438\u0442": {
        "\u043a": 6
    },
    "\u041f\u0456\u0442": {
        "\u043a": 2
    },
    "\u0430 \u041f": {
        "\u0438": 2
    },
    "\u0430\u0439\u0440": {
        "\u043d": 1
    },
    "\u0430\u043c\u0441": {
        "\u0442": 2
    },
    "\u0432\u0430 ": {
        "\u041f": 2
    },
    "\u0432\u0438 ": {
        "\u041f": 1
    },
    "\u0434\u0430\u043c": {
        "\u0441": 2
    },
    "\u0435\u0440\u043d": {
        "\u0441": 1
    },
    "\u0438 \u041f": {
        "\u0456": 1
    },
    "\u0438\u0442\u043a": {
        "\u0430": 2,
        "\u0435": 2,
        "\u044d": 2
    },
    "\u043a\u0430\u0439": {
        "\u0440": 1
    },
    "\u043a\u0430\u0440": {
        "\u043d": 1
    },
    "\u043a\u0435\u0440": {
        "\u043d": 4
    },
    "\u043a\u044d\u0440": {
        "\u043d": 2
    },
    "\u043a\u0456 ": {
        "\u043e": 1
    },
    "\u043c\u0441\u0442": {
        "\u0430": 2
    },
    "\u043d\u0441\u044c": {
        "\u043a": 1
    },
    "\u043e\u0432\u0430": {
        " ": 1
    },
    "\u043e\u0432\u0438": {
        " ": 1
    },
    "\u043e\u0441\u0442": {
        "\u0440": 1
    },
    "\u0440\u0432\u0430": {
        " ": 1
    },
    "\u0440\u043d\u0441": {
        "\u044c": 1
    },
    "\u0440\u043e\u0432": {
        "\u0430": 1,
        "\u0438": 2
    },
    "\u0441\u0442\u0430": {
        "\u0443": 1,
        "\u045e": 1
    },
    "\u0441\u0442\u0440": {
        "\u0432": 1,
        "\u043e": 3
    },
    "\u0441\u044c\u043a": {
        "\u0456": 1
    },
    "\u0442\u0430\u0443": {
        "\u043d": 1
    },
    "\u0442\u0430\u045e": {
        "\u043d": 1
    },
    "\u0442\u043a\u0430": {
        "\u0439": 1,
        "\u0440": 1
    },
    "\u0442\u043a\u0435": {
        "\u0440": 4
    },
    "\u0442\u043a\u044d": {
        "\u0440": 2
    },
    "\u0442\u0440\u0432": {
        "\u0430": 1
    },
    "\u0442\u0440\u043e": {
        "\u0432": 3
    },
    "\u044c\u043a\u0456": {
        " ": 1
    },
    "\u0456 \u043e": {
        "\u0441": 1
    },
    "\u0456\u0442\u043a": {
        "\u0435": 2
    },
    "\u05d0\u05d3\u05de": {
        "\u05e1": 1
    },
    "\u05d3\u05de\u05e1": {
        "\u05d8": 1
    },
    "\u05d8\u05d0\u05d5": {
        "\u05df": 1
    },
    "\u05d8\u05e7\u05e8": {
        "\u05df": 1
    },
    "\u05d9\u05d8\u05e7": {
        "\u05e8": 1
    },
    "\u05de\u05e1\u05d8": {
        "\u05d0": 1
    },
    "\u05e1\u05d8\u05d0": {
        "\u05d5": 1
    },
    "\u05e4\u05d9\u05d8": {
        "\u05e7": 1
    },
    "\u060c \u062c": {
        "\u0632": 1
    },
    "\u060c \u067e": {
        "\u06cc": 1
    },
    "\u0622\u062f\u0645": {
        "\u0632": 1
    },
    "\u0624\u0646\u060c": {
        " ": 1
    },
    "\u0626\u0631 ": {
        "\u067e": 1
    },
    "\u0626\u0631\u0646": {
        " ": 1
    },
    "\u0627\u0624\u0646": {
        "\u060c": 1
    },
    "\u0627\u0626\u0631": {
        " ": 1,
        "\u0646": 1
    },
    "\u0627\u062f\u0645": {
        "\u0632": 1
    },
    "\u0627\u06cc\u0631": {
        " ": 1
    },
    "\u0627\u06cc\u0633": {
        "\u0644": 1
    },
    "\u0627\u06cc\u0688": {
        "\u0645": 1
    },
    "\u0628\u064a\u062a": {
        "\u0643": 1
    },
    "\u062a\u0627\u0648": {
        "\u0646": 1
    },
    "\u062a\u0643\u064a": {
        "\u0631": 1
    },
    "\u062a\u0648\u0646": {
        "\u060c": 1
    },
    "\u062a\u06a9\u0631": {
        "\u0646": 1
    },
    "\u062a\u200c\u06a9": {
        "\u0631": 1
    },
    "\u062c\u0632\u0627": {
        "\u0626": 2,
        "\u06cc": 1
    },
    "\u062c\u0632\u0631": {
        " ": 1
    },
    "\u062f\u0645\u0632": {
        "\u062a": 2
    },
    "\u0631 \u0628": {
        "\u064a": 1
    },
    "\u0631 \u067e": {
        "\u0679": 1,
        "\u06cc": 1
    },
    "\u0631\u0646 ": {
        "\u0627": 1,
        "\u062c": 1
    },
    "\u0632 \u0679": {
        "\u0627": 1
    },
    "\u0632\u0627\u0626": {
        "\u0631": 2
    },
    "\u0632\u0627\u06cc": {
        "\u0631": 1
    },
    "\u0632\u062a\u0627": {
        "\u0648": 1
    },
    "\u0632\u062a\u0648": {
        "\u0646": 1
    },
    "\u0632\u0631 ": {
        "\u0628": 1
    },
    "\u0633\u0644\u0646": {
        "\u062f": 1
    },
    "\u0643\u064a\u0631": {
        "\u0646": 1
    },
    "\u0645\u0632 ": {
        "\u0679": 1
    },
    "\u0645\u0632\u062a": {
        "\u0627": 1,
        "\u0648": 1
    },
    "\u0646 \u0627": {
        "\u06cc": 1
    },
    "\u0646 \u062c": {
        "\u0632": 1
    },
    "\u0646\u060c ": {
        "\u062c": 1,
        "\u067e": 1
    },
    "\u0648\u0646\u060c": {
        " ": 1
    },
    "\u064a\u062a\u0643": {
        "\u064a": 1
    },
    "\u0679\u0627\u0624": {
        "\u0646": 1
    },
    "\u0679\u06a9\u0627": {
        "\u0626": 1
    },
    "\u0679\u06a9\u06cc": {
        "\u0631": 1
    },
    "\u067e\u0679\u06a9": {
        "\u0627": 1,
        "\u06cc": 1
    },
    "\u067e\u06cc\u062a": {
        "\u06a9": 1,
        "\u200c": 1
    },
    "\u0688\u0645\u0632": {
        " ": 1
    },
    "\u06a9\u0627\u0626": {
        "\u0631": 1
    },
    "\u06a9\u0631\u0646": {
        " ": 1
    },
    "\u06a9\u06cc\u0631": {
        "\u0646": 1
    },
    "\u06cc\u062a\u06a9": {
        "\u0631": 1
    },
    "\u06cc\u062a\u200c": {
        "\u06a9": 1
    },
    "\u06cc\u0631 ": {
        "\u067e": 1
    },
    "\u06cc\u0633\u0644": {
        "\u0646": 1
    },
    "\u06cc\u0688\u0645": {
        "\u0632": 1
    },
    "\u0907\u0930\u094d": {
        "\u0928": 1
    },
    "\u0915\u093e\u0907": {
        "\u0930": 1
    },
    "\u0915\u0948\u0930": {
        "\u094d": 1
    },
    "\u091f\u0915\u093e": {
        "\u0907": 1
    },
    "\u091f\u0915\u0948": {
        "\u0930": 1
    },
    "\u091f\u093e\u0909": {
        "\u0928": 1
    },
    "\u0921\u092e\u094d": {
        "\u0938": 1
    },
    "\u092a\u093f\u091f": {
        "\u0915": 2
    },
    "\u092e\u094d\u0938": {
        "\u091f": 1
    },
    "\u0938\u091f\u093e": {
        "\u0909": 1
    },
    "\u093e\u0907\u0930": {
        "\u094d": 1
    },
    "\u093f\u091f\u0915": {
        "\u093e": 1,
        "\u0948": 1
    },
    "\u0948\u0930\u094d": {
        "\u0928": 1
    },
    "\u094d\u0938\u091f": {
        "\u093e": 1
    },
    "\u0972\u0921\u092e": {
        "\u094d": 1
    },
    "\u0995\u09c7\u09af": {
        "\u09bc": 1
    },
    "\u099f\u0995\u09c7": {
        "\u09af": 1
    },
    "\u09aa\u09bf\u099f": {
        "\u0995": 1
    },
    "\u09af\u09bc\u09be": {
        "\u09b0": 1
    },
    "\u09bc\u09be\u09b0": {
        "\u09cd": 1
    },
    "\u09be\u09b0\u09cd": {
        "\u09a8": 1
    },
    "\u09bf\u099f\u0995": {
        "\u09c7": 1
    },
    "\u09c7\u09af\u09bc": {
        "\u09be": 1
    },
    "\u0a95\u0ac8\u0ab0": {
        "\u0acd": 1
    },
    "\u0a9f\u0a95\u0ac8": {
        "\u0ab0": 1
    },
    "\u0aaa\u0ac0\u0a9f": {
        "\u0a95": 1
    },
    "\u0ac0\u0a9f\u0a95": {
        "\u0ac8": 1
    },
    "\u0ac8\u0ab0\u0acd": {
        "\u0aa8": 1
    },
    "\u0b07\u0b30\u0b3f": {
        "\u0b28": 1
    },
    "\u0b15\u0b3e\u0b07": {
        "\u0b30": 1
    },
    "\u0b1f\u0b15\u0b3e": {
        "\u0b07": 1
    },
    "\u0b2a\u0b3f\u0b1f": {
        "\u0b15": 1
    },
    "\u0b30\u0b3f\u0b28": {
        "\u0b4d": 1
    },
    "\u0b3e\u0b07\u0b30": {
        "\u0b3f": 1
    },
    "\u0b3f\u0b1f\u0b15": {
        "\u0b3e": 1
    },
    "\u0b86\u0b9f\u0bae": {
        "\u0bcd": 1
    },
    "\u0b95\u0bc6\u0baf": {
        "\u0bcd": 1
    },
    "\u0b9f\u0bae\u0bcd": {
        "\u0bb8": 1
    },
    "\u0b9f\u0bb5\u0bc1": {
        "\u0ba9": 1
    },
    "\u0b9f\u0bcd\u0b95": {
        "\u0bc6": 1
    },
    "\u0baa\u0bbf\u0b9f": {
        "\u0bcd": 1
    },
    "\u0bae\u0bcd\u0bb8": {
        "\u0bcd": 1
    },
    "\u0baf\u0bcd\u0bb0": {
        "\u0bcd": 1
    },
    "\u0bb0\u0bcd\u0ba9": {
        "\u0bcd": 1
    },
    "\u0bb5\u0bc1\u0ba9": {
        "\u0bcd": 1
    },
    "\u0bb8\u0bcd\u0b9f": {
        "\u0bb5": 1
    },
    "\u0bbf\u0b9f\u0bcd": {
        "\u0b95": 1
    },
    "\u0bc6\u0baf\u0bcd": {
        "\u0bb0": 1
    },
    "\u0bcd\u0b95\u0bc6": {
        "\u0baf": 1
    },
    "\u0bcd\u0b9f\u0bb5": {
        "\u0bc1": 1
    },
    "\u0bcd\u0bb0\u0bcd": {
        "\u0ba9": 1
    },
    "\u0bcd\u0bb8\u0bcd": {
        "\u0b9f": 1
    },
    "\u0c15\u0c46\u0c30": {
        "\u0c4d": 1
    },
    "\u0c1f\u0c4d\u0c15": {
        "\u0c46": 1
    },
    "\u0c2a\u0c3f\u0c1f": {
        "\u0c4d": 1
    },
    "\u0c30\u0c4d\u0c28": {
        "\u0c4d": 1
    },
    "\u0c3f\u0c1f\u0c4d": {
        "\u0c15": 1
    },
    "\u0c46\u0c30\u0c4d": {
        "\u0c28": 1
    },
    "\u0c4d\u0c15\u0c46": {
        "\u0c30": 1
    },
    "\u0c95\u0cc8\u0cb0": {
        "\u0ccd": 1
    },
    "\u0c9f\u0ccd\u200c": {
        "\u0c95": 1
    },
    "\u0caa\u0cbf\u0c9f": {
        "\u0ccd": 1
    },
    "\u0cb0\u0ccd\u0ca8": {
        "\u0ccd": 1
    },
    "\u0cbf\u0c9f\u0ccd": {
        "\u200c": 1
    },
    "\u0cc8\u0cb0\u0ccd": {
        "\u0ca8": 1
    },
    "\u0ccd\u200c\u0c95": {
        "\u0cc8": 1
    },
    "\u0d15\u0d46\u0d2f": {
        "\u0d4d": 1
    },
    "\u0d2a\u0d3f\u0d31": {
        "\u0d4d": 1
    },
    "\u0d2f\u0d4d\u0d28": {
        "\u0d4d": 1
    },
    "\u0d31\u0d4d\u0d15": {
        "\u0d46": 1
    },
    "\u0d31\u0d4d\u0d31": {
        "\u0d4d": 1
    },
    "\u0d3f\u0d31\u0d4d": {
        "\u0d31": 1
    },
    "\u0d46\u0d2f\u0d4d": {
        "\u0d28": 1
    },
    "\u0d4d\u0d15\u0d46": {
        "\u0d2f": 1
    },
    "\u0d4d\u0d28\u0d4d": {
        "\u200d": 1
    },
    "\u0d4d\u0d31\u0d4d": {
        "\u0d15": 1
    },
    "\u0d9a\u0dd9\u0dba": {
        "\u0dca": 1
    },
    "\u0da7\u0dca\u0d9a": {
        "\u0dd9": 1
    },
    "\u0daf\u0dd6\u0db4": {
        "\u0dad": 1
    },
    "\u0db1\u0dca ": {
        "\u0daf": 1
    },
    "\u0db4\u0dd2\u0da7": {
        "\u0dca": 1
    },
    "\u0dba\u0dca\u0db1": {
        "\u0dca": 1
    },
    "\u0dca \u0daf": {
        "\u0dd6": 1
    },
    "\u0dca\u0d9a\u0dd9": {
        "\u0dba": 1
    },
    "\u0dca\u0db1\u0dca": {
        " ": 1
    },
    "\u0dd2\u0da7\u0dca": {
        "\u0d9a": 1
    },
    "\u0dd6\u0db4\u0dad": {
        "\u0dca": 1
    },
    "\u0dd9\u0dba\u0dca": {
        "\u0db1": 1
    },
    "\u0e01\u0e32\u0e30": {
        "\u0e1e": 1
    },
    "\u0e04\u0e23\u0e4c": {
        "\u0e19": 2
    },
    "\u0e14\u0e31\u0e21": {
        "\u0e2a": 1
    },
    "\u0e15\u0e41\u0e04": {
        "\u0e23": 2
    },
    "\u0e17\u0e32\u0e27": {
        "\u0e19": 1
    },
    "\u0e1e\u0e34\u0e15": {
        "\u0e41": 2
    },
    "\u0e21\u0e2a\u0e4c": {
        "\u0e17": 1
    },
    "\u0e21\u0e39\u0e48": {
        "\u0e40": 1
    },
    "\u0e2a\u0e4c\u0e17": {
        "\u0e32": 1
    },
    "\u0e2b\u0e21\u0e39": {
        "\u0e48": 1
    },
    "\u0e2d\u0e14\u0e31": {
        "\u0e21": 1
    },
    "\u0e30\u0e1e\u0e34": {
        "\u0e15": 1
    },
    "\u0e31\u0e21\u0e2a": {
        "\u0e4c": 1
    },
    "\u0e32\u0e27\u0e19": {
        "\u0e4c": 1
    },
    "\u0e32\u0e30\u0e1e": {
        "\u0e34": 1
    },
    "\u0e34\u0e15\u0e41": {
        "\u0e04": 2
    },
    "\u0e39\u0e48\u0e40": {
        "\u0e01": 1
    },
    "\u0e40\u0e01\u0e32": {
        "\u0e30": 1
    },
    "\u0e41\u0e04\u0e23": {
        "\u0e4c": 2
    },
    "\u0e41\u0e2d\u0e14": {
        "\u0e31": 1
    },
    "\u0e48\u0e40\u0e01": {
        "\u0e32": 1
    },
    "\u0e4c\u0e17\u0e32": {
        "\u0e27": 1
    },
    "\u10d0\u10d3\u10d0": {
        "\u10db": 1
    },
    "\u10d0\u10db\u10e1": {
        "\u10e2": 1
    },
    "\u10d0\u10e3\u10dc": {
        "\u10d8": 1
    },
    "\u10d3\u10d0\u10db": {
        "\u10e1": 1
    },
    "\u10db\u10e1\u10e2": {
        "\u10d0": 1
    },
    "\u10e1\u10e2\u10d0": {
        "\u10e3": 1
    },
    "\u10e2\u10d0\u10e3": {
        "\u10dc": 1
    },
    "\u1275\u12ab\u12a2": {
        "\u122d": 1
    },
    "\u12ab\u12a2\u122d": {
        "\u1295": 1
    },
    "\u1352\u1275\u12ab": {
        "\u12a2": 1
    },
    "\u1ea3o ": {
        "P": 1
    },
    "\u1ea7n ": {
        "\u0111": 1
    },
    "\u1eb9\u0301\u00e8": {
        "d": 1
    },
    "\u200c\u06a9\u0631": {
        "\u0646": 1
    },
    "\u200c\u0c95\u0cc8": {
        "\u0cb0": 1
    },
    "\u2019s ": {
        "I": 1
    },
    "\u30a2\u30c0\u30e0": {
        "\u30b9": 1
    },
    "\u30a2\u30f3\u8af8": {
        "\u5cf6": 1
    },
    "\u30aa\u30a8\u30ce": {
        "\u5cf6": 1
    },
    "\u30b1\u30a2\u30f3": {
        "\u5cf6": 1,
        "\u8af8": 1
    },
    "\u30b9\u30bf\u30a6": {
        "\u30f3": 1
    },
    "\u30c0\u30e0\u30b9": {
        "\u30bf": 1
    },
    "\u30c0\u30fc\u30bd": {
        "\u30f3": 1
    },
    "\u30c8\u30b1\u30a2": {
        "\u30f3": 2
    },
    "\u30d4\u30c8\u30b1": {
        "\u30a2": 2
    },
    "\u30d8\u30f3\u30c0": {
        "\u30fc": 1
    },
    "\u30e0\u30b9\u30bf": {
        "\u30a6": 1
    },
    "\u30f3\u30c0\u30fc": {
        "\u30bd": 1
    },
    "\u30fc\u30bd\u30f3": {
        "\u5cf6": 1
    },
    "\u4e9a\u5f53\u65af": {
        "\u6566": 1
    },
    "\u51ef\u6069\u7fa4": {
        "\u5c9b": 1
    },
    "\u7279\u51ef\u6069": {
        "\u7fa4": 1
    },
    "\u76ae\u7279\u51ef": {
        "\u6069": 1
    },
    "\ub364\uc2a4\ud0c0": {
        "\uc6b4": 1
    },
    "\uc560\ub364\uc2a4": {
        "\ud0c0": 1
    },
    "\uc5b8 \uc81c": {
        "\ub3c4": 1
    },
    "\ucf00\uc5b8 ": {
        "\uc81c": 1
    },
    "\ud54f\ucf00\uc5b8": {
        " ": 1,
        "\uc12c": 1
    }
}